{"meta": {"fund_house": "PPFAS Mutual Fund", "scheme_type": "Open Ended Schemes", "scheme_category": "Equity Scheme - Flexi Cap Fund", "scheme_code": 153964, "scheme_name": "Parag Parikh Flexi Cap Fund - Direct Plan - IDCW", "isin_growth": null, "isin_div_reinvestment": "INF879O01308"}, "data": [{"date": "10-12-2025", "nav": "94.51750"}, {"date": "09-12-2025", "nav": "94.56630"}, {"date": "08-12-2025", "nav": "94.80560"}, {"date": "05-12-2025", "nav": "95.37160"}, {"date": "04-12-2025", "nav": "94.94580"}, {"date": "03-12-2025", "nav": "94.84710"}, {"date": "02-12-2025", "nav": "94.75220"}, {"date": "01-12-2025", "nav": "94.93970"}, {"date": "28-11-2025", "nav": "95.00170"}, {"date": "27-11-2025", "nav": "94.85630"}, {"date": "26-11-2025", "nav": "94.99520"}, {"date": "25-11-2025", "nav": "94.38830"}, {"date": "24-11-2025", "nav": "94.42310"}, {"date": "21-11-2025", "nav": "94.41090"}, {"date": "20-11-2025", "nav": "94.41790"}, {"date": "19-11-2025", "nav": "94.30860"}, {"date": "18-11-2025", "nav": "94.06290"}, {"date": "17-11-2025", "nav": "94.51010"}, {"date": "14-11-2025", "nav": "94.28990"}, {"date": "13-11-2025", "nav": "94.00590"}, {"date": "12-11-2025", "nav": "94.17070"}, {"date": "11-11-2025", "nav": "94.17980"}, {"date": "10-11-2025", "nav": "94.07650"}, {"date": "07-11-2025", "nav": "93.54280"}, {"date": "06-11-2025", "nav": "93.77900"}, {"date": "04-11-2025", "nav": "93.83410"}, {"date": "03-11-2025", "nav": "94.45770"}, {"date": "31-10-2025", "nav": "94.40650"}], "status": "SUCCESS"}